[
    {
        "type": "message",
        "text": "",
        "files": [
            {
                "id": "F04THD7E8UT",
                "created": 1678566990,
                "timestamp": 1678566990,
                "name": "IMG_9500.jpg",
                "title": "IMG_9500",
                "mimetype": "image\/jpeg",
                "filetype": "jpg",
                "pretty_type": "JPEG",
                "user": "U04GY24PLTY",
                "user_team": "T04C9T53QJK",
                "editable": false,
                "size": 124097,
                "mode": "hosted",
                "is_external": false,
                "external_type": "",
                "is_public": true,
                "public_url_shared": false,
                "display_as_bot": false,
                "username": "",
                "url_private": "https:\/\/files.slack.com\/files-pri\/T04C9T53QJK-F04THD7E8UT\/img_9500.jpg?t=xoxe-4417923126631-5022377271139-5015905004086-b2b4520b10e0c24cdacc10ba8537aebb",
                "url_private_download": "https:\/\/files.slack.com\/files-pri\/T04C9T53QJK-F04THD7E8UT\/download\/img_9500.jpg?t=xoxe-4417923126631-5022377271139-5015905004086-b2b4520b10e0c24cdacc10ba8537aebb",
                "media_display_type": "unknown",
                "thumb_64": "https:\/\/files.slack.com\/files-tmb\/T04C9T53QJK-F04THD7E8UT-f92ecb4212\/img_9500_64.jpg?t=xoxe-4417923126631-5022377271139-5015905004086-b2b4520b10e0c24cdacc10ba8537aebb",
                "thumb_80": "https:\/\/files.slack.com\/files-tmb\/T04C9T53QJK-F04THD7E8UT-f92ecb4212\/img_9500_80.jpg?t=xoxe-4417923126631-5022377271139-5015905004086-b2b4520b10e0c24cdacc10ba8537aebb",
                "thumb_360": "https:\/\/files.slack.com\/files-tmb\/T04C9T53QJK-F04THD7E8UT-f92ecb4212\/img_9500_360.jpg?t=xoxe-4417923126631-5022377271139-5015905004086-b2b4520b10e0c24cdacc10ba8537aebb",
                "thumb_360_w": 249,
                "thumb_360_h": 360,
                "thumb_480": "https:\/\/files.slack.com\/files-tmb\/T04C9T53QJK-F04THD7E8UT-f92ecb4212\/img_9500_480.jpg?t=xoxe-4417923126631-5022377271139-5015905004086-b2b4520b10e0c24cdacc10ba8537aebb",
                "thumb_480_w": 332,
                "thumb_480_h": 480,
                "thumb_160": "https:\/\/files.slack.com\/files-tmb\/T04C9T53QJK-F04THD7E8UT-f92ecb4212\/img_9500_160.jpg?t=xoxe-4417923126631-5022377271139-5015905004086-b2b4520b10e0c24cdacc10ba8537aebb",
                "thumb_720": "https:\/\/files.slack.com\/files-tmb\/T04C9T53QJK-F04THD7E8UT-f92ecb4212\/img_9500_720.jpg?t=xoxe-4417923126631-5022377271139-5015905004086-b2b4520b10e0c24cdacc10ba8537aebb",
                "thumb_720_w": 499,
                "thumb_720_h": 720,
                "thumb_800": "https:\/\/files.slack.com\/files-tmb\/T04C9T53QJK-F04THD7E8UT-f92ecb4212\/img_9500_800.jpg?t=xoxe-4417923126631-5022377271139-5015905004086-b2b4520b10e0c24cdacc10ba8537aebb",
                "thumb_800_w": 554,
                "thumb_800_h": 800,
                "thumb_960": "https:\/\/files.slack.com\/files-tmb\/T04C9T53QJK-F04THD7E8UT-f92ecb4212\/img_9500_960.jpg?t=xoxe-4417923126631-5022377271139-5015905004086-b2b4520b10e0c24cdacc10ba8537aebb",
                "thumb_960_w": 665,
                "thumb_960_h": 960,
                "thumb_1024": "https:\/\/files.slack.com\/files-tmb\/T04C9T53QJK-F04THD7E8UT-f92ecb4212\/img_9500_1024.jpg?t=xoxe-4417923126631-5022377271139-5015905004086-b2b4520b10e0c24cdacc10ba8537aebb",
                "thumb_1024_w": 709,
                "thumb_1024_h": 1024,
                "original_w": 710,
                "original_h": 1025,
                "thumb_tiny": "AwAwACG623dkzEY4IzTQoAH79jg560hYeYxfaBkjlOfzpmcJjemD38ugCyzoVI3j0zVVbYsPlkU\/nTsoHwWUAYyNnWrMZQrlBgfTFNOwmkyt9lf\/AJ6UfZX\/AOelW6KOZi5UQlfmJ3yDnOBQFwRmSQ49qGHJ4HX2o2nsP5UiiTePRvypQwJwM\/lURXB6D9KVAQeOPXpQBLRRRQBBKPmB9aQKoDE0MxJHGeKgun+6C2wdSO5NT1KImkZdp6+oqdG5Rg6Lk8jPbFV12B\/lfLdTQ5VmJLpu7ijUp2Zobl\/vr+dG5f76\/nVXyx\/dFHlj+6KVxWP\/2Q==",
                "permalink": "https:\/\/actualize-day-2022-12.slack.com\/files\/U04GY24PLTY\/F04THD7E8UT\/img_9500.jpg",
                "permalink_public": "https:\/\/slack-files.com\/T04C9T53QJK-F04THD7E8UT-c96ebcd83b",
                "is_starred": false,
                "has_rich_preview": false,
                "file_access": "visible"
            }
        ],
        "upload": false,
        "user": "U04GY24PLTY",
        "display_as_bot": false,
        "ts": "1678566997.021139",
        "client_msg_id": "C6E5B410-ED29-4DA9-8185-E87483E7C0FD",
        "reactions": [
            {
                "name": "joy",
                "users": [
                    "U04DLUZMY84",
                    "U04HB4D6ARZ",
                    "U04DLUZGJ4C"
                ],
                "count": 3
            }
        ]
    },
    {
        "type": "message",
        "text": "",
        "files": [
            {
                "id": "F04THMEPT19",
                "created": 1678583020,
                "timestamp": 1678583020,
                "name": "Screenshot_20230311-170300.png",
                "title": "Screenshot_20230311-170300.png",
                "mimetype": "image\/png",
                "filetype": "png",
                "pretty_type": "PNG",
                "user": "U04HB4DFQ0K",
                "user_team": "T04C9T53QJK",
                "editable": false,
                "size": 2277719,
                "mode": "hosted",
                "is_external": false,
                "external_type": "",
                "is_public": true,
                "public_url_shared": false,
                "display_as_bot": false,
                "username": "",
                "url_private": "https:\/\/files.slack.com\/files-pri\/T04C9T53QJK-F04THMEPT19\/screenshot_20230311-170300.png?t=xoxe-4417923126631-5022377271139-5015905004086-b2b4520b10e0c24cdacc10ba8537aebb",
                "url_private_download": "https:\/\/files.slack.com\/files-pri\/T04C9T53QJK-F04THMEPT19\/download\/screenshot_20230311-170300.png?t=xoxe-4417923126631-5022377271139-5015905004086-b2b4520b10e0c24cdacc10ba8537aebb",
                "media_display_type": "unknown",
                "thumb_64": "https:\/\/files.slack.com\/files-tmb\/T04C9T53QJK-F04THMEPT19-ea1e0cee92\/screenshot_20230311-170300_64.png?t=xoxe-4417923126631-5022377271139-5015905004086-b2b4520b10e0c24cdacc10ba8537aebb",
                "thumb_80": "https:\/\/files.slack.com\/files-tmb\/T04C9T53QJK-F04THMEPT19-ea1e0cee92\/screenshot_20230311-170300_80.png?t=xoxe-4417923126631-5022377271139-5015905004086-b2b4520b10e0c24cdacc10ba8537aebb",
                "thumb_360": "https:\/\/files.slack.com\/files-tmb\/T04C9T53QJK-F04THMEPT19-ea1e0cee92\/screenshot_20230311-170300_360.png?t=xoxe-4417923126631-5022377271139-5015905004086-b2b4520b10e0c24cdacc10ba8537aebb",
                "thumb_360_w": 360,
                "thumb_360_h": 289,
                "thumb_480": "https:\/\/files.slack.com\/files-tmb\/T04C9T53QJK-F04THMEPT19-ea1e0cee92\/screenshot_20230311-170300_480.png?t=xoxe-4417923126631-5022377271139-5015905004086-b2b4520b10e0c24cdacc10ba8537aebb",
                "thumb_480_w": 480,
                "thumb_480_h": 386,
                "thumb_160": "https:\/\/files.slack.com\/files-tmb\/T04C9T53QJK-F04THMEPT19-ea1e0cee92\/screenshot_20230311-170300_160.png?t=xoxe-4417923126631-5022377271139-5015905004086-b2b4520b10e0c24cdacc10ba8537aebb",
                "original_w": 638,
                "original_h": 513,
                "thumb_tiny": "AwAmADDPoqe3jVvmbJwenpx3p4gRR1Lkp279OlAFWirBt1yfn+UZy3pyKX7OmRy3PbIz1xQBWoqy0CAY3HPIGMe\/X8qZLEqRhlJOTjPHPHWgCNQD1BP0p20f3HpqkDqM\/jS7x6fqaAF24Odj+1G+XdnLZ6Um8f3f1NG8f3f1NACbW\/un8qGZzgMTx2NBbPQY\/GkoASiiigAooooAKKKKAP\/Z",
                "permalink": "https:\/\/actualize-day-2022-12.slack.com\/files\/U04HB4DFQ0K\/F04THMEPT19\/screenshot_20230311-170300.png",
                "permalink_public": "https:\/\/slack-files.com\/T04C9T53QJK-F04THMEPT19-4da449c3fa",
                "is_starred": false,
                "has_rich_preview": false,
                "file_access": "visible"
            }
        ],
        "upload": true,
        "user": "U04HB4DFQ0K",
        "display_as_bot": false,
        "ts": "1678583023.208609",
        "client_msg_id": "919ad1e8-aed4-4478-a47e-f68a4e150916",
        "thread_ts": "1678583023.208609",
        "reply_count": 3,
        "reply_users_count": 2,
        "latest_reply": "1678724479.288149",
        "reply_users": [
            "U04HL79B12M",
            "U04J9382JP3"
        ],
        "replies": [
            {
                "user": "U04HL79B12M",
                "ts": "1678723472.711369"
            },
            {
                "user": "U04J9382JP3",
                "ts": "1678724476.478589"
            },
            {
                "user": "U04J9382JP3",
                "ts": "1678724479.288149"
            }
        ],
        "is_locked": false,
        "subscribed": false,
        "reactions": [
            {
                "name": "+1",
                "users": [
                    "U04D3UXCN3Z"
                ],
                "count": 1
            },
            {
                "name": "joy",
                "users": [
                    "U04HL79B12M",
                    "U04HB4D6ARZ",
                    "U04DLUZMY84"
                ],
                "count": 3
            }
        ]
    }
]